{"DefensiveReboundsA": 28, "OffensiveReboundsB": 17, "OffensiveReboundsA": 10, "DefensiveReboundsB": 19, "TurnoversStartersA": 9, "TurnoversBenchA": 1, "TurnoversStartersB": 3, "TurnoversBenchB": 5, "StealsStartersA": 5, "StealsBenchA": 0, "StealsStartersB": 1, "StealsBenchB": 2, "AssistsStartersA": 12, "AssistsBenchA": 4, "AssistsStartersB": 9, "AssistsBenchB": 1, "PointsStartersA": 87, "PointsBenchA": 10, "PointsStartersB": 36, "PointsBenchB": 45, "maxA": 10, "minutePrevA": 10, "prevA": "29-21", "minuteStrA": 12, "strA": "39-21", "maxB": 7, "minutePrevB": 25, "prevB": "67-48", "minuteStrB": 26, "strB": "67-55", "maxLeadA": 19, "maxLeadB": 3, "minuteMaxLeadA": 24, "minuteMaxLeadB": 1, "puntosMaxLeadA": "64-45", "puntosMaxLeadB": "0-3", "minutoActual": 1, "isLive": false}